README
plotexplorer_gui.py
setup.py
plotexplorer_gui.egg-info/PKG-INFO
plotexplorer_gui.egg-info/SOURCES.txt
plotexplorer_gui.egg-info/dependency_links.txt
plotexplorer_gui.egg-info/not-zip-safe
plotexplorer_gui.egg-info/requires.txt
plotexplorer_gui.egg-info/top_level.txt