Metadata-Version: 1.1
Name: plotexplorer-gui
Version: 0.4.1
Summary: A wxpython/matplotlib script for plotting and contrasting a collection of graphs
Home-page: https://bitbucket.org/robochat/plotexplorer_gui
Author: robochat
Author-email: rjsteed@talk21.com
License: BSD
Keywords: matplotlib
Platform: UNKNOWN
Classifier: License :: OSI Approved :: BSD License
Classifier: Programming Language :: Python :: 2
Classifier: Development Status :: 4 - Beta
Classifier: Intended Audience :: Developers
Classifier: Intended Audience :: Science/Research
Classifier: Natural Language :: English
Classifier: Operating System :: OS Independent
Classifier: Topic :: Scientific/Engineering :: Visualization
